toopazo_tools/__init__.py
toopazo_tools/data2d.py
toopazo_tools/external_process.py
toopazo_tools/file_folder.py
toopazo_tools/matplotlib.py
toopazo_tools/pandas.py
toopazo_tools/replace_dots_from_path.py
toopazo_tools/telemetry.py
toopazo_tools/time_series.py
toopazo_tools-0.0.62.dist-info/LICENSE
toopazo_tools-0.0.62.dist-info/METADATA
toopazo_tools-0.0.62.dist-info/WHEEL
toopazo_tools-0.0.62.dist-info/top_level.txt
toopazo_tools-0.0.62.dist-info/RECORD
