Metadata-Version: 2.1
Name: toopazo-tools
Version: 0.0.62
Summary: Python methods for common file and folder operations
Home-page: https://github.com/toopazo/toopazo_tools
Author: toopazo
Author-email: toopazo@protonmail.com
License: UNKNOWN
Platform: UNKNOWN
Classifier: Programming Language :: Python :: 3
Classifier: License :: OSI Approved :: MIT License
Classifier: Operating System :: OS Independent
Requires-Python: >=3.6
License-File: LICENSE
